tokentally/__init__.py
tokentally/_version.py
tokentally/client.py
tokentally/types.py
tokentally-0.2.0.dist-info/licenses/LICENSE
tokentally-0.2.0.dist-info/METADATA
tokentally-0.2.0.dist-info/WHEEL
tokentally-0.2.0.dist-info/top_level.txt
tokentally-0.2.0.dist-info/RECORD
