Metadata-Version: 2.4
Name: tokentally
Version: 0.2.0
Summary: Track AI API usage with TokenTally
Home-page: https://github.com/tokentally/tokentally-python
Author: TokenTally
Author-email: TokenTally <support@tokentally.io>
License-Expression: MIT
Project-URL: Homepage, https://github.com/tokentally/tokentally-python
Project-URL: Repository, https://github.com/tokentally/tokentally-python
Classifier: Development Status :: 4 - Beta
Classifier: Intended Audience :: Developers
Classifier: Operating System :: OS Independent
Classifier: Programming Language :: Python :: 3
Classifier: Programming Language :: Python :: 3.8
Classifier: Programming Language :: Python :: 3.9
Classifier: Programming Language :: Python :: 3.10
Classifier: Programming Language :: Python :: 3.11
Classifier: Programming Language :: Python :: 3.12
Classifier: Topic :: Software Development :: Libraries :: Python Modules
Requires-Python: >=3.8
License-File: LICENSE
Requires-Dist: httpx>=0.24.0
Provides-Extra: dev
Requires-Dist: pytest>=7.0.0; extra == "dev"
Requires-Dist: pytest-asyncio>=0.21.0; extra == "dev"
Requires-Dist: respx>=0.20.0; extra == "dev"
Dynamic: author
Dynamic: home-page
Dynamic: license-file
Dynamic: requires-python
